{
  "venue": "Rockanje",
  "seasonNum": "5",
  "weekNum": "1",
  "date": "Jan 22 to Jan 28",
  "isSig": false,
  "doubleBonus": false,
  "players": [
    {
      "name": "Colly45x",
      "console": "Xbox",
      "division": 1,
      "toPar": "-8",
      "putt": "",
      "shot": "",
      "ace": "",
      "alby": ""
    },
    {
      "name": "Keep_of_Kalessin",
      "console": "PS",
      "division": 1,
      "toPar": "-7",
      "putt": "",
      "shot": "",
      "ace": "",
      "alby": ""
    },
    {
      "name": "x3offthetee",
      "console": "Xbox",
      "division": 1,
      "toPar": "-2",
      "putt": "40.8",
      "shot": "",
      "ace": "",
      "alby": ""
    },
    {
      "name": "Tenbobnote",
      "console": "PS",
      "division": 1,
      "toPar": "E",
      "putt": "",
      "shot": "15.3",
      "ace": "",
      "alby": ""
    },
    {
      "name": "Mr Longpole",
      "console": "Xbox",
      "division": 1,
      "toPar": "+3",
      "putt": "",
      "shot": "",
      "ace": "",
      "alby": ""
    },
    {
      "name": "Geordieboy85",
      "console": "PS",
      "division": 1,
      "toPar": "+3",
      "putt": "",
      "shot": "",
      "ace": "",
      "alby": ""
    },
    {
      "name": "iluvJeezus",
      "console": "Xbox",
      "division": 2,
      "toPar": "-10",
      "putt": "37.1",
      "shot": "",
      "ace": "",
      "alby": ""
    },
    {
      "name": "er114ic",
      "console": "PS",
      "division": 2,
      "toPar": "-1",
      "putt": "",
      "shot": "",
      "ace": "",
      "alby": ""
    },
    {
      "name": "Hoplinkz",
      "console": "PS",
      "division": 2,
      "toPar": "+2",
      "putt": "",
      "shot": "",
      "ace": "",
      "alby": ""
    },
    {
      "name": "NoWorries37908",
      "console": "Xbox",
      "division": 2,
      "toPar": "+4",
      "putt": "",
      "shot": "6.9",
      "ace": "",
      "alby": ""
    },
    {
      "name": "Polekatt",
      "console": "PC",
      "division": 2,
      "toPar": "+19",
      "putt": "",
      "shot": "",
      "ace": "",
      "alby": ""
    },
    {
      "name": "Horusphoenix",
      "console": "Xbox",
      "division": 2,
      "toPar": "",
      "putt": "",
      "shot": "",
      "ace": "",
      "alby": ""
    },
    {
      "name": "WingisBack",
      "console": "PS",
      "division": 3,
      "toPar": "-12",
      "putt": "56.8",
      "shot": "",
      "ace": "",
      "alby": ""
    },
    {
      "name": "SimChars68",
      "console": "PC",
      "division": 3,
      "toPar": "+6",
      "putt": "",
      "shot": "",
      "ace": "",
      "alby": ""
    },
    {
      "name": "zdubz92",
      "console": "PS",
      "division": 3,
      "toPar": "+7",
      "putt": "",
      "shot": "",
      "ace": "",
      "alby": ""
    },
    {
      "name": "GovernmentAgent",
      "console": "PC",
      "division": 3,
      "toPar": "+17",
      "putt": "",
      "shot": "11.2",
      "ace": "",
      "alby": ""
    },
    {
      "name": "bfctino",
      "console": "PS",
      "division": 3,
      "toPar": "+22",
      "putt": "",
      "shot": "",
      "ace": "",
      "alby": ""
    },
    {
      "name": "BotClappintonll",
      "console": "PS",
      "division": 3,
      "toPar": "+35",
      "putt": "",
      "shot": "",
      "ace": "",
      "alby": ""
    }
  ],
  "season": {
    "Colly45x": {
      "points": 100,
      "eventsPlayed": 1
    },
    "Keep_of_Kalessin": {
      "points": 90,
      "eventsPlayed": 1
    },
    "x3offthetee": {
      "points": 105,
      "eventsPlayed": 1
    },
    "Tenbobnote": {
      "points": 95,
      "eventsPlayed": 1
    },
    "Mr Longpole": {
      "points": 60,
      "eventsPlayed": 1
    },
    "Geordieboy85": {
      "points": 60,
      "eventsPlayed": 1
    },
    "iluvJeezus": {
      "points": 125,
      "eventsPlayed": 1
    },
    "er114ic": {
      "points": 90,
      "eventsPlayed": 1
    },
    "Hoplinkz": {
      "points": 80,
      "eventsPlayed": 1
    },
    "NoWorries37908": {
      "points": 95,
      "eventsPlayed": 1
    },
    "Polekatt": {
      "points": 60,
      "eventsPlayed": 1
    },
    "WingisBack": {
      "points": 125,
      "eventsPlayed": 1
    },
    "SimChars68": {
      "points": 90,
      "eventsPlayed": 1
    },
    "zdubz92": {
      "points": 80,
      "eventsPlayed": 1
    },
    "GovernmentAgent": {
      "points": 95,
      "eventsPlayed": 1
    },
    "bfctino": {
      "points": 60,
      "eventsPlayed": 1
    },
    "BotClappintonll": {
      "points": 50,
      "eventsPlayed": 1
    }
  },
  "historyHtml": "<div class=\"history-item\" style=\"margin-bottom:20px; border-left:4px solid var(--secondary); padding-left:15px;\">\n\t\t\t\t\t<strong style=\"color:#37474f;\">S5 W1: Rockanje</strong><table width=\"100%\" style=\"font-size:12px;\"><tr><th colspan=\"3\" style=\"text-align:left; background:#eee; padding:2px 5px;\">Division 1</th></tr><tr><td>Colly45x</td><td>-8</td><td style=\"font-weight:bold;\">100</td></tr><tr><td>Keep_of_Kalessin</td><td>-7</td><td style=\"font-weight:bold;\">90</td></tr><tr><td>x3offthetee</td><td>-2</td><td style=\"font-weight:bold;\">105</td></tr><tr><td>Tenbobnote</td><td>E</td><td style=\"font-weight:bold;\">95</td></tr><tr><td>Mr Longpole</td><td>+3</td><td style=\"font-weight:bold;\">60</td></tr><tr><td>Geordieboy85</td><td>+3</td><td style=\"font-weight:bold;\">60</td></tr><tr><th colspan=\"3\" style=\"text-align:left; background:#eee; padding:2px 5px;\">Division 2</th></tr><tr><td>iluvJeezus</td><td>-10</td><td style=\"font-weight:bold;\">125</td></tr><tr><td>er114ic</td><td>-1</td><td style=\"font-weight:bold;\">90</td></tr><tr><td>Hoplinkz</td><td>+2</td><td style=\"font-weight:bold;\">80</td></tr><tr><td>NoWorries37908</td><td>+4</td><td style=\"font-weight:bold;\">95</td></tr><tr><td>Polekatt</td><td>+19</td><td style=\"font-weight:bold;\">60</td></tr><tr><th colspan=\"3\" style=\"text-align:left; background:#eee; padding:2px 5px;\">Division 3</th></tr><tr><td>WingisBack</td><td>-12</td><td style=\"font-weight:bold;\">125</td></tr><tr><td>SimChars68</td><td>+6</td><td style=\"font-weight:bold;\">90</td></tr><tr><td>zdubz92</td><td>+7</td><td style=\"font-weight:bold;\">80</td></tr><tr><td>GovernmentAgent</td><td>+17</td><td style=\"font-weight:bold;\">95</td></tr><tr><td>bfctino</td><td>+22</td><td style=\"font-weight:bold;\">60</td></tr><tr><td>BotClappintonll</td><td>+35</td><td style=\"font-weight:bold;\">50</td></tr></table></div>"
}